{
	"info": {
		"_postman_id": "2b9e5b76-75c4-4746-9119-b27a5524ef96",
		"name": "PosTech - TC4",
		"schema": "https://schema.getpostman.com/json/collection/v2.1.0/collection.json",
		"_exporter_id": "44632007"
	},
	"item": [
		{
			"name": "ms-usuario",
			"item": [
				{
					"name": "Busca usuario por username",
					"request": {
						"method": "GET",
						"header": [],
						"url": {
							"raw": "{{HOST_MS_USUARIO}}/users/username/{{username}}",
							"host": [
								"{{HOST_MS_USUARIO}}"
							],
							"path": [
								"users",
								"username",
								"{{username}}"
							]
						}
					},
					"response": []
				},
				{
					"name": "Busca usuario por username - Username inexistente",
					"request": {
						"method": "GET",
						"header": [],
						"url": {
							"raw": "{{HOST_MS_USUARIO}}/users/username/{{username}}",
							"host": [
								"{{HOST_MS_USUARIO}}"
							],
							"path": [
								"users",
								"username",
								"{{username}}"
							]
						}
					},
					"response": []
				},
				{
					"name": "Busca usuario por id",
					"request": {
						"method": "GET",
						"header": [],
						"url": {
							"raw": "{{HOST_MS_USUARIO}}/users/{{id}}",
							"host": [
								"{{HOST_MS_USUARIO}}"
							],
							"path": [
								"users",
								"{{id}}"
							]
						}
					},
					"response": []
				},
				{
					"name": "Busca usuario por id - Id inexistente",
					"request": {
						"method": "GET",
						"header": [],
						"url": {
							"raw": "{{HOST_MS_USUARIO}}/users/{{id}}",
							"host": [
								"{{HOST_MS_USUARIO}}"
							],
							"path": [
								"users",
								"{{id}}"
							]
						}
					},
					"response": []
				},
				{
					"name": "Atualizar usuario",
					"request": {
						"method": "PUT",
						"header": [],
						"body": {
							"mode": "raw",
							"raw": "{\n  \"username\": \"gustavo.rodrigues23\",\n  \"name\": \"gu rodrigues\",\n  \"password\": \"Password@123\",\n  \"email\": \"gu.rod@email.com\",\n  \"roleEnum\": \"ADMIN\",\n  \"activeUser\": true\n}",
							"options": {
								"raw": {
									"language": "json"
								}
							}
						},
						"url": {
							"raw": "{{HOST_MS_USUARIO}}/users/{{id}}",
							"host": [
								"{{HOST_MS_USUARIO}}"
							],
							"path": [
								"users",
								"{{id}}"
							]
						}
					},
					"response": []
				},
				{
					"name": "Atualizar usuario - Campos ausentes",
					"request": {
						"method": "PUT",
						"header": [],
						"body": {
							"mode": "raw",
							"raw": "{\n  \"username\": \"\",\n  \"name\": \"\",\n  \"password\": \"\",\n  \"email\": \"\",\n  \"roleEnum\": \"ADMIN\",\n  \"activeUser\": true\n}",
							"options": {
								"raw": {
									"language": "json"
								}
							}
						},
						"url": {
							"raw": "{{HOST_MS_USUARIO}}/users/{{id}}",
							"host": [
								"{{HOST_MS_USUARIO}}"
							],
							"path": [
								"users",
								"{{id}}"
							]
						}
					},
					"response": []
				},
				{
					"name": "Deleta usuario",
					"request": {
						"method": "DELETE",
						"header": [],
						"url": {
							"raw": "{{HOST_MS_USUARIO}}/users/{{id}}",
							"host": [
								"{{HOST_MS_USUARIO}}"
							],
							"path": [
								"users",
								"{{id}}"
							]
						}
					},
					"response": []
				},
				{
					"name": "Deleta usuario - Id inexistente",
					"request": {
						"method": "DELETE",
						"header": [],
						"url": {
							"raw": "{{HOST_MS_USUARIO}}/users/{{id}}",
							"host": [
								"{{HOST_MS_USUARIO}}"
							],
							"path": [
								"users",
								"{{id}}"
							]
						}
					},
					"response": []
				},
				{
					"name": "Insere usuario",
					"request": {
						"method": "POST",
						"header": [],
						"body": {
							"mode": "raw",
							"raw": "{\n  \"username\": \"thalita\",\n  \"name\": \"thalita silva\",\n  \"password\": \"Password@123\",\n  \"email\": \"tha.silva@email.com\",\n  \"roleEnum\": \"ADMIN\",\n  \"activeUser\": true\n}",
							"options": {
								"raw": {
									"language": "json"
								}
							}
						},
						"url": {
							"raw": "{{HOST_MS_USUARIO}}/users",
							"host": [
								"{{HOST_MS_USUARIO}}"
							],
							"path": [
								"users"
							]
						}
					},
					"response": []
				},
				{
					"name": "Insere usuario - Campos ausentes",
					"request": {
						"method": "POST",
						"header": [],
						"body": {
							"mode": "raw",
							"raw": "{\n  \"username\": \"\",\n  \"name\": \"\",\n  \"password\": \"\",\n  \"email\": \"\",\n  \"roleEnum\": \"\",\n  \"activeUser\": true\n}",
							"options": {
								"raw": {
									"language": "json"
								}
							}
						},
						"url": {
							"raw": "{{HOST_MS_USUARIO}}/users",
							"host": [
								"{{HOST_MS_USUARIO}}"
							],
							"path": [
								"users"
							]
						}
					},
					"response": []
				}
			]
		},
		{
			"name": "ms-login",
			"item": [
				{
					"name": "Login - Sucesso",
					"event": [
						{
							"listen": "test",
							"script": {
								"exec": [
									"var jsonData = pm.response.json();",
									"pm.environment.set(\"jwt_admin\", jsonData.token);"
								],
								"type": "text/javascript",
								"packages": {},
								"requests": {}
							}
						}
					],
					"request": {
						"auth": {
							"type": "noauth"
						},
						"method": "POST",
						"header": [],
						"body": {
							"mode": "raw",
							"raw": "{\n    \"username\": \"gustavo.rodrigues\",\n    \"password\": \"teste123\"\n}",
							"options": {
								"raw": {
									"language": "json"
								}
							}
						},
						"url": {
							"raw": "{{HOST_MS_LOGIN}}/login",
							"host": [
								"{{HOST_MS_LOGIN}}"
							],
							"path": [
								"login"
							]
						}
					},
					"response": []
				},
				{
					"name": "Login - Senha Errada",
					"event": [
						{
							"listen": "test",
							"script": {
								"exec": [
									"var jsonData = pm.response.json();",
									"pm.environment.set(\"jwt_admin\", jsonData.token);"
								],
								"type": "text/javascript",
								"packages": {},
								"requests": {}
							}
						}
					],
					"request": {
						"auth": {
							"type": "noauth"
						},
						"method": "POST",
						"header": [],
						"body": {
							"mode": "raw",
							"raw": "{\n    \"username\": \"leonardo.rod\",\n    \"password\": \"teste123456\"\n}",
							"options": {
								"raw": {
									"language": "json"
								}
							}
						},
						"url": {
							"raw": "{{HOST_MS_LOGIN}}/login",
							"host": [
								"{{HOST_MS_LOGIN}}"
							],
							"path": [
								"login"
							]
						}
					},
					"response": []
				},
				{
					"name": "Login - Sem credenciais nenhuma",
					"event": [
						{
							"listen": "test",
							"script": {
								"exec": [
									"var jsonData = pm.response.json();",
									"pm.environment.set(\"jwt_admin\", jsonData.token);"
								],
								"type": "text/javascript",
								"packages": {},
								"requests": {}
							}
						}
					],
					"request": {
						"auth": {
							"type": "noauth"
						},
						"method": "POST",
						"header": [],
						"body": {
							"mode": "raw",
							"raw": "{\n    \"username\": \"gustavo.rodrigues\",\n    \"password\": \"teste123\"\n}",
							"options": {
								"raw": {
									"language": "json"
								}
							}
						},
						"url": {
							"raw": "{{HOST_MS_LOGIN}}/login",
							"host": [
								"{{HOST_MS_LOGIN}}"
							],
							"path": [
								"login"
							]
						}
					},
					"response": []
				},
				{
					"name": "Register",
					"event": [
						{
							"listen": "test",
							"script": {
								"exec": [
									"var jsonData = pm.response.json();",
									"pm.environment.set(\"jwt_admin\", jsonData.token);"
								],
								"type": "text/javascript",
								"packages": {},
								"requests": {}
							}
						}
					],
					"request": {
						"auth": {
							"type": "noauth"
						},
						"method": "POST",
						"header": [],
						"body": {
							"mode": "raw",
							"raw": "{\n    \"username\": \"ghhustavo.rod\",\n    \"name\": \"ghhustavo rod\",\n    \"password\": \"gu106249\",\n    \"email\": \"guh@email.com\",\n    \"roleEnum\": \"USER\",\n    \"activeUser\": true\n}",
							"options": {
								"raw": {
									"language": "json"
								}
							}
						},
						"url": {
							"raw": "{{HOST_MS_LOGIN}}/register",
							"host": [
								"{{HOST_MS_LOGIN}}"
							],
							"path": [
								"register"
							]
						}
					},
					"response": []
				},
				{
					"name": "Register - Dados faltando",
					"event": [
						{
							"listen": "test",
							"script": {
								"exec": [
									"var jsonData = pm.response.json();",
									"pm.environment.set(\"jwt_admin\", jsonData.token);"
								],
								"type": "text/javascript",
								"packages": {},
								"requests": {}
							}
						}
					],
					"request": {
						"auth": {
							"type": "noauth"
						},
						"method": "POST",
						"header": [],
						"body": {
							"mode": "raw",
							"raw": "{\n    \"username\": \" \",\n    \"name\": \" \",\n    \"password\": \" \",\n    \"email\": \"sid@email.com\",\n    \"roleEnum\": \"USER\",\n    \"activeUser\": true\n}",
							"options": {
								"raw": {
									"language": "json"
								}
							}
						},
						"url": {
							"raw": "{{HOST_MS_LOGIN}}/register",
							"host": [
								"{{HOST_MS_LOGIN}}"
							],
							"path": [
								"register"
							]
						}
					},
					"response": []
				},
				{
					"name": "Refresh - RefreshToken já usado",
					"event": [
						{
							"listen": "test",
							"script": {
								"exec": [
									"var jsonData = pm.response.json();",
									"pm.environment.set(\"jwt_admin\", jsonData.token);"
								],
								"type": "text/javascript",
								"packages": {},
								"requests": {}
							}
						}
					],
					"request": {
						"auth": {
							"type": "bearer",
							"bearer": [
								{
									"key": "token",
									"value": "eyJhbGciOiJIUzI1NiJ9.eyJzdWIiOiJndXN0YXZvLnJvZHJpZ3VlcyIsInRva2VuX3R5cGUiOiJhY2Nlc3MiLCJ1c2VySWQiOiIxIiwicm9sZSI6IkFETUlOIiwiZXhwIjoxNzYxNzAxNDk4fQ.vyJXeKsOUDNpNSqvKjMLMjKvHfMMglJeOWyXZI7VDSY",
									"type": "string"
								}
							]
						},
						"method": "POST",
						"header": [],
						"body": {
							"mode": "raw",
							"raw": "{\n  \"refreshToken\": \"eyJhbGciOiJIUzI1NiJ9.eyJzdWIiOiJsZW9uYXJkby5yb2QiLCJ0b2tlbl90eXBlIjoicmVmcmVzaCIsImV4cCI6MTc2NzM4MjIzOX0.5FDYURvLVdTvjz5sfTCDTR7N4bjh7hxReDGlJ5RYwX8\"\n}",
							"options": {
								"raw": {
									"language": "json"
								}
							}
						},
						"url": {
							"raw": "{{HOST_MS_LOGIN}}/refresh",
							"host": [
								"{{HOST_MS_LOGIN}}"
							],
							"path": [
								"refresh"
							]
						}
					},
					"response": []
				},
				{
					"name": "Refresh - Sucesso",
					"event": [
						{
							"listen": "test",
							"script": {
								"exec": [
									"var jsonData = pm.response.json();",
									"pm.environment.set(\"jwt_admin\", jsonData.token);"
								],
								"type": "text/javascript",
								"packages": {},
								"requests": {}
							}
						}
					],
					"request": {
						"auth": {
							"type": "bearer",
							"bearer": [
								{
									"key": "token",
									"value": "eyJhbGciOiJIUzI1NiJ9.eyJzdWIiOiJndXN0YXZvLnJvZHJpZ3VlcyIsInRva2VuX3R5cGUiOiJhY2Nlc3MiLCJ1c2VySWQiOiIxIiwicm9sZSI6IkFETUlOIiwiZXhwIjoxNzYxNzAxNDk4fQ.vyJXeKsOUDNpNSqvKjMLMjKvHfMMglJeOWyXZI7VDSY",
									"type": "string"
								}
							]
						},
						"method": "POST",
						"header": [],
						"body": {
							"mode": "raw",
							"raw": "{\n  \"refreshToken\": \"eyJhbGciOiJIUzI1NiJ9.eyJzdWIiOiJsZW9uYXJkby5yb2QiLCJ0b2tlbl90eXBlIjoicmVmcmVzaCIsImV4cCI6MTc2NzM4MjIzOX0.5FDYURvLVdTvjz5sfTCDTR7N4bjh7hxReDGlJ5RYwX8\"\n}",
							"options": {
								"raw": {
									"language": "json"
								}
							}
						},
						"url": {
							"raw": "{{HOST_MS_LOGIN}}/refresh",
							"host": [
								"{{HOST_MS_LOGIN}}"
							],
							"path": [
								"refresh"
							]
						}
					},
					"response": []
				},
				{
					"name": "Logout",
					"event": [
						{
							"listen": "test",
							"script": {
								"exec": [
									"var jsonData = pm.response.json();",
									"pm.environment.set(\"jwt_admin\", jsonData.token);"
								],
								"type": "text/javascript",
								"packages": {},
								"requests": {}
							}
						}
					],
					"request": {
						"auth": {
							"type": "bearer",
							"bearer": [
								{
									"key": "token",
									"value": "eyJhbGciOiJIUzI1NiJ9.eyJzdWIiOiJndXN0YXZvLnJvZHJpZ3VlcyIsInRva2VuX3R5cGUiOiJhY2Nlc3MiLCJ1c2VySWQiOiIxIiwicm9sZSI6IkFETUlOIiwiZXhwIjoxNzYxNzAxNDk4fQ.vyJXeKsOUDNpNSqvKjMLMjKvHfMMglJeOWyXZI7VDSY",
									"type": "string"
								}
							]
						},
						"method": "POST",
						"header": [],
						"body": {
							"mode": "raw",
							"raw": "{\n  \"refreshToken\": \"eyJhbGciOiJIUzI1NiJ9.eyJzdWIiOiJzaWRuZWkucm9kIiwidG9rZW5fdHlwZSI6InJlZnJlc2giLCJleHAiOjE3Njc0ODIyNDV9.i_PCv70PYRSYBMcZzcnv1tQvEtUXJGJ8O6fC1fQehgg\"\n}",
							"options": {
								"raw": {
									"language": "json"
								}
							}
						},
						"url": {
							"raw": "{{HOST_MS_LOGIN}}/logout",
							"host": [
								"{{HOST_MS_LOGIN}}"
							],
							"path": [
								"logout"
							]
						}
					},
					"response": []
				},
				{
					"name": "Logout - RefreshToken errado",
					"event": [
						{
							"listen": "test",
							"script": {
								"exec": [
									"var jsonData = pm.response.json();",
									"pm.environment.set(\"jwt_admin\", jsonData.token);"
								],
								"type": "text/javascript",
								"packages": {},
								"requests": {}
							}
						}
					],
					"request": {
						"auth": {
							"type": "bearer",
							"bearer": [
								{
									"key": "token",
									"value": "",
									"type": "string"
								}
							]
						},
						"method": "POST",
						"header": [],
						"body": {
							"mode": "raw",
							"raw": "{\n  \"refreshToken\": \"eyJhbGciOiJIUzI1NiJ9.eyJzdWIiOiJzaWRuZWkucm9kIiwidG9rZW5fdHlwZSI6ImFjY2VzcyIsInVzZXJJZCI6IjY5NGYzMTVlNDU1YTZjN2ZiY2YxN2VlYiIsInJvbGUiOiJVU0VSIiwiZXhwIjoxNzY2ODgwOTA3fQ.D743clPBR-AIGI-hSLARVv_M56PY9d9jO9OkUbCIj8A\"\n}",
							"options": {
								"raw": {
									"language": "json"
								}
							}
						},
						"url": {
							"raw": "{{HOST_MS_LOGIN}}/logout",
							"host": [
								"{{HOST_MS_LOGIN}}"
							],
							"path": [
								"logout"
							]
						}
					},
					"response": []
				}
			]
		},
		{
			"name": "ms-feedback",
			"item": [
				{
					"name": "Busca Todos Feedbacks",
					"request": {
						"method": "GET",
						"header": [],
						"url": {
							"raw": "{{HOST_MS_FEEDBACK}}/feedback?description&urgencyType=LOW&limit&offset",
							"host": [
								"{{HOST_MS_FEEDBACK}}"
							],
							"path": [
								"feedback"
							],
							"query": [
								{
									"key": "description",
									"value": null
								},
								{
									"key": "urgencyType",
									"value": "LOW",
									"description": "Use URGENT, HIGH, MEDIUM or LOW "
								},
								{
									"key": "limit",
									"value": null
								},
								{
									"key": "offset",
									"value": null
								}
							]
						}
					},
					"response": []
				},
				{
					"name": "Busca id Feedback",
					"request": {
						"method": "GET",
						"header": [],
						"url": {
							"raw": "{{HOST_MS_FEEDBACK}}/feedback/{{id}}",
							"host": [
								"{{HOST_MS_FEEDBACK}}"
							],
							"path": [
								"feedback",
								"{{id}}"
							],
							"query": [
								{
									"key": "",
									"value": null,
									"disabled": true
								}
							]
						}
					},
					"response": []
				},
				{
					"name": "Atualiza Feedback",
					"request": {
						"method": "PUT",
						"header": [],
						"body": {
							"mode": "raw",
							"raw": "{\n  \"description\": \"Excellent service.\",\n  \"rating\": 8,\n  \"urgencyType\": \"LOW\"\n}",
							"options": {
								"raw": {
									"language": "json"
								}
							}
						},
						"url": {
							"raw": "{{HOST_MS_FEEDBACK}}/feedback/{{id}}",
							"host": [
								"{{HOST_MS_FEEDBACK}}"
							],
							"path": [
								"feedback",
								"{{id}}"
							]
						}
					},
					"response": []
				},
				{
					"name": "Delete Feedback",
					"request": {
						"method": "DELETE",
						"header": [],
						"body": {
							"mode": "raw",
							"raw": "",
							"options": {
								"raw": {
									"language": "json"
								}
							}
						},
						"url": {
							"raw": "{{HOST_MS_FEEDBACK}}/feedback/{{id}}",
							"host": [
								"{{HOST_MS_FEEDBACK}}"
							],
							"path": [
								"feedback",
								"{{id}}"
							]
						}
					},
					"response": []
				},
				{
					"name": "Inserir Feedback",
					"request": {
						"auth": {
							"type": "bearer",
							"bearer": [
								{
									"key": "token",
									"value": "eyJhbGciOiJIUzI1NiJ9.eyJzdWIiOiJndXN0YXZvLnJvZHJpZ3VlcyIsInRva2VuX3R5cGUiOiJhY2Nlc3MiLCJ1c2VySWQiOiI2OTUxNzk4MDAxODY1MjExZDUyNGZhZjIiLCJyb2xlIjoiVVNFUiIsImV4cCI6MTc2Njk1MDg1Mn0.fQiGQXTyVoyG0sFsiQ5uN1HYpMDFGuOHZ4imgORP5m0",
									"type": "string"
								}
							]
						},
						"method": "POST",
						"header": [],
						"body": {
							"mode": "raw",
							"raw": "{\n  \"description\": \"Excelente opnião sobre o sistema\",\n  \"rating\": 8,\n  \"urgencyType\": \"LOW\"\n}",
							"options": {
								"raw": {
									"language": "json"
								}
							}
						},
						"url": {
							"raw": "{{HOST_MS_FEEDBACK}}/feedback",
							"host": [
								"{{HOST_MS_FEEDBACK}}"
							],
							"path": [
								"feedback"
							]
						}
					},
					"response": []
				}
			]
		}
	],
	"variable": [
		{
			"key": "HOST_MS_USUARIO",
			"value": "",
			"type": "default"
		},
		{
			"key": "HOST_MS_LOGIN",
			"value": "",
			"type": "default"
		},
		{
			"key": "HOST_MS_FEEDBACK",
			"value": "",
			"type": "default"
		}
	]
}